TransportNSW/__init__.py
TransportNSW/transportnsw.py
PyTransportNSW-0.1.1.dist-info/LICENSE
PyTransportNSW-0.1.1.dist-info/METADATA
PyTransportNSW-0.1.1.dist-info/WHEEL
PyTransportNSW-0.1.1.dist-info/top_level.txt
PyTransportNSW-0.1.1.dist-info/RECORD
