Metadata-Version: 2.1
Name: PyTransportNSW
Version: 0.1.1
Summary: Get transport information from TransportNSW
Home-page: https://github.com/Dav0815/TransportNSW
Author: Dav0815
License: UNKNOWN
Platform: UNKNOWN
Classifier: Programming Language :: Python :: 3
Classifier: License :: OSI Approved :: MIT License
Classifier: Operating System :: OS Independent
Classifier: Intended Audience :: Developers
Classifier: Topic :: Software Development :: Libraries :: Python Modules
